lab2hub/__init__.py
lab2hub/_version.py
lab2hub/labextension/package.json
lab2hub/labextension/static/534.752942e77971b236b839.js
lab2hub/labextension/static/568.40cb7824b4a2941e3896.js
lab2hub/labextension/static/568.5a6528089930bdf09a6f.js
lab2hub/labextension/static/remoteEntry.5255f4002360d1463554.js
lab2hub/labextension/static/remoteEntry.7f4b03d583c7ebf9d266.js
lab2hub/labextension/static/style.js
lab2hub-0.1.1.data/data/share/jupyter/labextensions/lab2hub/install.json
lab2hub-0.1.1.data/data/share/jupyter/labextensions/lab2hub/package.json
lab2hub-0.1.1.data/data/share/jupyter/labextensions/lab2hub/static/534.752942e77971b236b839.js
lab2hub-0.1.1.data/data/share/jupyter/labextensions/lab2hub/static/568.5a6528089930bdf09a6f.js
lab2hub-0.1.1.data/data/share/jupyter/labextensions/lab2hub/static/remoteEntry.5255f4002360d1463554.js
lab2hub-0.1.1.data/data/share/jupyter/labextensions/lab2hub/static/style.js
lab2hub-0.1.1.dist-info/LICENSE
lab2hub-0.1.1.dist-info/METADATA
lab2hub-0.1.1.dist-info/WHEEL
lab2hub-0.1.1.dist-info/top_level.txt
lab2hub-0.1.1.dist-info/RECORD
